chronos_ai/__init__.py
chronos_ai/analyze_stock_headlines.py
chronos_ai/CONSTANTS.py
chronos_ai/create_ticker_list.py
chronos_ai/data/nasdaq_screener_1711270178562.csv
chronos_ai/extract_ticker_headlines.py
chronos_ai/get_full_article_text.py
chronos_ai/get_yf_ticker_news.py
chronos_ai-0.1.0.dist-info/entry_points.txt
chronos_ai-0.1.0.dist-info/METADATA
chronos_ai-0.1.0.dist-info/WHEEL
chronos_ai-0.1.0.dist-info/RECORD
