Metadata-Version: 2.1
Name: chronos_ai
Version: 0.1.0
Summary: 
Author: David Piper
Author-email: dbpiper@gmail.com
Requires-Python: >=3.11,<4.0
Classifier: Programming Language :: Python :: 3
Classifier: Programming Language :: Python :: 3.11
Classifier: Programming Language :: Python :: 3.12
Requires-Dist: beautifulsoup4 (>=4.12.3,<5.0.0)
Requires-Dist: einops (>=0.7.0,<0.8.0)
Requires-Dist: graphene-django (>=3.2.0,<4.0.0)
Requires-Dist: numpy (>=1.26.3,<2.0.0)
Requires-Dist: pandas (>=2.1.4,<3.0.0)
Requires-Dist: pydash (>=7.0.7,<8.0.0)
Requires-Dist: python-immutable (>=1.0.2,<2.0.0)
Requires-Dist: python-redux (>=0.10.7,<0.11.0)
Requires-Dist: pytorch_lightning (>=2.1.3,<3.0.0)
Requires-Dist: scikit-learn (>=1.3.2,<2.0.0)
Requires-Dist: scrapy (>=2.11.1,<3.0.0)
Requires-Dist: spacy (>=3.7.4,<4.0.0)
Requires-Dist: spacytextblob (>=4.0.0,<5.0.0)
Requires-Dist: speech-user-interface (>=0.1.2,<0.2.0)
Requires-Dist: tenacity (>=8.2.3,<9.0.0)
Requires-Dist: torch (>=2.2.2,<3.0.0)
Requires-Dist: tqdm (>=4.66.2,<5.0.0)
Requires-Dist: tsfresh (>=0.20.2,<0.21.0)
Requires-Dist: urwid (>=2.6.1,<3.0.0)
Requires-Dist: yahoo_fin (>=0.8.9.1,<0.9.0.0)
Requires-Dist: yahoofinancials (>=1.2.0,<2.0.0)
Requires-Dist: yfinance (>=0.2.37,<0.3.0)
